runtime_builder.py
quex_runtime_builder-0.0.1.dist-info/LICENSE
quex_runtime_builder-0.0.1.dist-info/METADATA
quex_runtime_builder-0.0.1.dist-info/WHEEL
quex_runtime_builder-0.0.1.dist-info/top_level.txt
quex_runtime_builder-0.0.1.dist-info/RECORD
