Metadata-Version: 2.1
Name: quex_runtime_builder
Version: 0.0.1
Summary: Allow automatic builds in edit mode
Author-email: Richard Kiss <him@richardkiss.com>
License: Copyright 2023 by Richard Kiss
License-File: LICENSE
